leap.mail-0.3.9_1_gc1f9c92-py2.7-nspkg.pth
leap/mail/utils.py
leap/mail/decorators.py
leap/mail/messageflow.py
leap/mail/walk.py
leap/mail/__init__.py
leap/mail/load_tests.py
leap/mail/_version.py
leap/mail/size.py
leap/mail/smtp/__init__.py
leap/mail/smtp/gateway.py
leap/mail/smtp/rfc3156.py
leap/mail/smtp/tests/test_gateway.py
leap/mail/smtp/tests/__init__.py
leap/mail/imap/soledadstore.py
leap/mail/imap/memorystore.py
leap/mail/imap/interfaces.py
leap/mail/imap/__init__.py
leap/mail/imap/parser.py
leap/mail/imap/fields.py
leap/mail/imap/server.py
leap/mail/imap/fetch.py
leap/mail/imap/account.py
leap/mail/imap/messages.py
leap/mail/imap/mailbox.py
leap/mail/imap/messageparts.py
leap/mail/imap/index.py
leap/mail/imap/tests/imapclient.py
leap/mail/imap/tests/__init__.py
leap/mail/imap/tests/test_imap.py
leap/mail/imap/tests/walktree.py
leap/mail/imap/service/__init__.py
leap/mail/imap/service/imap.py
leap/mail/imap/service/manhole.py
leap.mail-0.3.9_1_gc1f9c92.dist-info/top_level.txt
leap.mail-0.3.9_1_gc1f9c92.dist-info/DESCRIPTION.rst
leap.mail-0.3.9_1_gc1f9c92.dist-info/pydist.json
leap.mail-0.3.9_1_gc1f9c92.dist-info/METADATA
leap.mail-0.3.9_1_gc1f9c92.dist-info/namespace_packages.txt
leap.mail-0.3.9_1_gc1f9c92.dist-info/WHEEL
leap.mail-0.3.9_1_gc1f9c92.dist-info/RECORD
