Metadata-Version: 2.0
Name: leap.mail
Version: 0.3.9-1-gc1f9c92
Summary: Mail Services provided by Bitmask, the LEAP Client.
Home-page: https://leap.se/
Author: Kali Kaneko
Author-email: kali@leap.se
License: GPLv3+
Download-URL: https://github.com/leapcode/leap_mail/archive/0.3.9.tar.gz
Platform: UNKNOWN
Classifier: Development Status :: 4 - Beta
Classifier: Framework :: Twisted
Classifier: Intended Audience :: Developers
Classifier: License :: OSI Approved :: GNU General Public License v3 (GPLv3)
Classifier: Operating System :: OS Independent
Classifier: Programming Language :: Python
Classifier: Programming Language :: Python :: 2.6
Classifier: Programming Language :: Python :: 2.7
Classifier: Topic :: Communications :: Email
Classifier: Topic :: Communications :: Email :: Post-Office :: IMAP
Classifier: Topic :: Communications :: Email :: Post-Office :: POP3
Classifier: Topic :: Internet
Classifier: Topic :: Security :: Cryptography
Classifier: Topic :: Software Development :: Libraries
Requires-Dist: zope.interface
Requires-Dist: leap.soledad.client (>=0.4.5)
Requires-Dist: leap.common (>=0.3.7)
Requires-Dist: leap.keymanager (>=0.3.8)
Requires-Dist: twisted
Requires-Dist: zope.proxy
Requires-Dist: enum
